robotframework_kwstats/__init__.py
robotframework_kwstats/html_helper.py
robotframework_kwstats/keyword_results.py
robotframework_kwstats/robotkwstats.py
robotframework_kwstats/runner.py
robotframework_kwstats-0.1.3.dist-info/LICENSE
robotframework_kwstats-0.1.3.dist-info/METADATA
robotframework_kwstats-0.1.3.dist-info/WHEEL
robotframework_kwstats-0.1.3.dist-info/entry_points.txt
robotframework_kwstats-0.1.3.dist-info/top_level.txt
robotframework_kwstats-0.1.3.dist-info/RECORD
