Metadata-Version: 2.1
Name: robotframework-kwstats
Version: 0.1.3
Summary: Report for keyword statistics
Home-page: https://github.com/adiralashiva8/robotframework-kwstats
Author: Shiva Prasad Adirala
Author-email: adiralashiva8@gmail.com
License: MIT
Keywords: robotframework keyword report
Platform: UNKNOWN
Classifier: Framework :: Robot Framework
Classifier: Programming Language :: Python
Classifier: Topic :: Software Development :: Testing
Requires-Dist: robotframework
Requires-Dist: beautifulsoup4
